separator/__init__.py
separator/formate_result.py
separator/separator.py
separator/separator_data/abbreviations.txt
separator/separator_data/separators.txt
separator/separator_data/starters.txt
separator/separator_data/terminators.txt
separator_vbar-1.1.dist-info/LICENSE
separator_vbar-1.1.dist-info/METADATA
separator_vbar-1.1.dist-info/WHEEL
separator_vbar-1.1.dist-info/top_level.txt
separator_vbar-1.1.dist-info/RECORD
